{
  "required": true,
  "minVersion": "0.8",
  "package": "net.modificationstation.stationapi.mixin.flattening",
  "compatibilityLevel": "JAVA_17",
  "mixins": [
    "BlockBaseAccessor",
    "ChunkAccessor",
    "MixinBlock",
    "MixinBlockBase",
    "MixinBlockWithEntity",
    "MixinChunk",
    "MixinClass417",
    "MixinClass467",
    "MixinDimension",
    "MixinEntityBase",
    "MixinFallingBlock",
    "MixinFire",
    "MixinItemBase",
    "MixinItemInstance",
    "MixinLevel",
    "MixinLevelMonsterSpawner",
    "MixinLevelProperties",
    "MixinNetherLevelSource",
    "MixinOverworldLevelSource",
    "MixinPlayerBase",
    "MixinPlayerInventory",
    "MixinSecondaryBlock",
    "MixinSkylandsLevelSource",
    "MixinWorldPopulationRegion",
    "MovingPistonBlockMixin",
    "PistonBlockEntityMixin",
    "PistonBlockMixin",
    "RegionFileAccessor"
  ],
  "client": [
    "client.MixinBaseClientInteractionManager",
    "client.MixinBlockRenderer",
    "client.MixinClientLevel",
    "client.MixinInGame",
    "client.MixinMinecraft",
    "client.MixinMultiplayerChunkCache",
    "client.MixinMultiPlayerClientInteractionManager",
    "client.MixinPlayerRenderer",
    "client.MixinSinglePlayerClientInteractionManager",
    "client.MixinWorldRenderer"
  ],
  "injectors": {
    "defaultRequire": 1
  },
  "server": [
    "server.class_514Accessor",
    "server.Mixinclass_514",
    "server.Mixinclass_70",
    "server.MixinMinecraftServer",
    "server.MixinServerPlayer",
    "server.MixinServerPlayerPacketHandler",
    "server.ServerPlayerViewAccessor"
  ]
}
